httpdo.py
setup.py
httpdo.egg-info/PKG-INFO
httpdo.egg-info/SOURCES.txt
httpdo.egg-info/dependency_links.txt
httpdo.egg-info/not-zip-safe
httpdo.egg-info/requires.txt
httpdo.egg-info/top_level.txt