Metadata-Version: 1.0
Name: httpdo
Version: 0.3
Summary: a scriptable httpd
Home-page: https://github.com/tengu/py-httpdo
Author: karasuyamatengu
Author-email: karasuyamatengu@gmail.com
License: LGPL
Platform: UNKNOWN
Classifier: License :: OSI Approved :: GNU Library or Lesser General Public License (LGPL)
Classifier: Programming Language :: Python
Classifier: Development Status :: 4 - Beta
Classifier: Environment :: Console
